<?xml version="1.0" encoding="UTF-8"?>
<Defs>

    <!-- TEST AREA -->
    <Core40k.ExtraDecorationDef Name="BEWH_TESTSTUFF" Abstract="True">
        <iconPath>Things/Decorations/Armor/Common/BEWH_Deco_DeathWatch_Shoulder_east</iconPath>
        <drawnTextureIconPath>Things/Decorations/Armor/Common/BEWH_Deco_DeathWatch_Shoulder</drawnTextureIconPath>
        <sortOrder>0</sortOrder>
        <defaultShowRotation>
            <li>North</li>
            <li>South</li>
            <li>West</li>
        </defaultShowRotation>
        <appliesTo>
            <li>BEWH_MkVIIPowerArmor</li>
            <li>BEWH_MkXPowerArmor</li>
        </appliesTo>
        <layerOffsets>
            <li>
                <key>South</key>
                <value>-10</value>
            </li>
            <li>
                <key>West</key>
                <value>-10</value>
            </li>
        </layerOffsets>
        <shaderType>Cutout</shaderType>
        <colourable>true</colourable>
        <flipable>true</flipable>
        <availablePresets>
            <li>BEWH_DecoPaletteGold</li>
            <li>BEWH_DecoPaletteGreen</li>
            <li>BEWH_DecoPaletteSilver</li>
            <li>BEWH_DecoPaletteIFBlack</li>
            <li>BEWH_DecoPaletteLeatherBrown</li>
            <li>BEWH_DecoPaletteLeatherBlack</li>
        </availablePresets>
    </Core40k.ExtraDecorationDef>
	
	<Core40k.ExtraDecorationDef>
        <defName>BEWH_HeadTest</defName>
        <label>HeadTest</label>
        <description>...</description>
        <iconPath>Things/Decorations/Armor/Common/BEWH_Deco_DeathWatch_Shoulder_west</iconPath>
        <drawnTextureIconPath>Things/Decorations/Armor/Common/BEWH_Deco_DeathWatch_Shoulder</drawnTextureIconPath>
        <sortOrder>0</sortOrder>
        <defaultShowRotation>
            <li>North</li>
            <li>South</li>
            <li>West</li>
        </defaultShowRotation>
        <appliesTo>
            <li>BEWH_MkVIIPowerArmor</li>
            <li>BEWH_MkXPowerArmor</li>
        </appliesTo>
        <layerOffsets>
            <li>
                <key>South</key>
                <value>-40</value>
            </li>
        </layerOffsets>
        <shaderType>Cutout</shaderType>
        <flipable>true</flipable>
        <drawInHeadSpace>true</drawInHeadSpace>
    </Core40k.ExtraDecorationDef>

    <!-- BODY STUFF -->
    <!-- Common -->

    <!-- Custom shoulders -->
    <Core40k.ExtraDecorationDef>
        <defName>BEWH_DecoDWatchPauldron</defName>
        <label>Deathwatch pauldron</label>
        <description>...</description>
        <iconPath>Things/Decorations/Armor/Common/BEWH_Deco_DeathWatch_Shoulder_west</iconPath>
        <drawnTextureIconPath>Things/Decorations/Armor/Common/BEWH_Deco_DeathWatch_Shoulder</drawnTextureIconPath>
        <sortOrder>0</sortOrder>
        <defaultShowRotation>
            <li>North</li>
            <li>South</li>
            <li>West</li>
        </defaultShowRotation>
        <appliesTo>
            <li>BEWH_MkVIIPowerArmor</li>
            <li>BEWH_MkXPowerArmor</li>
        </appliesTo>
        <layerOffsets>
            <li>
                <key>South</key>
                <value>-10</value>
            </li>
        </layerOffsets>
        <shaderType>Cutout</shaderType>
        <flipable>true</flipable>
    </Core40k.ExtraDecorationDef>

    <!-- Purity Seals -->
    <Core40k.ExtraDecorationDef>
        <defName>BEWH_DecoPSeal_1</defName>
        <label>Purity seals 1</label>
        <description>...</description>
        <iconPath>Things/Decorations/Armor/Common/PuritySeals/BEWH_Deco_PuritySeal1_south</iconPath>
        <drawnTextureIconPath>Things/Decorations/Armor/Common/PuritySeals/BEWH_Deco_PuritySeal1</drawnTextureIconPath>
        <sortOrder>0</sortOrder>
        <defaultShowRotation>
            <li>East</li>
            <li>South</li>
            <!-- <li>West</li> -->
            <li>North</li>
        </defaultShowRotation>
        <appliesTo>
            <li>BEWH_MkVIIPowerArmor</li>
            <li>BEWH_MkXPowerArmor</li>
        </appliesTo>
        <layerOffsets>
            <li>
                <key>North</key>
                <value>5</value>
            </li>
        </layerOffsets>
        <shaderType>Cutout</shaderType>
        <flipable>true</flipable>
    </Core40k.ExtraDecorationDef>

    <Core40k.ExtraDecorationDef>
        <defName>BEWH_DecoPSeal_2</defName>
        <label>Purity seals 2</label>
        <description>...</description>
        <iconPath>Things/Decorations/Armor/Common/PuritySeals/BEWH_Deco_PuritySeal2_south</iconPath>
        <drawnTextureIconPath>Things/Decorations/Armor/Common/PuritySeals/BEWH_Deco_PuritySeal2</drawnTextureIconPath>
        <sortOrder>0</sortOrder>
        <defaultShowRotation>
            <li>North</li>
            <li>South</li>
            <li>West</li>
        </defaultShowRotation>
        <appliesTo>
            <li>BEWH_MkVIIPowerArmor</li>
            <li>BEWH_MkXPowerArmor</li>
        </appliesTo>
        <shaderType>Cutout</shaderType>
        <flipable>true</flipable>
    </Core40k.ExtraDecorationDef>

    <Core40k.ExtraDecorationDef>
        <defName>BEWH_DecoPSeal_3</defName>
        <label>Purity seals 3</label>
        <description>...</description>
        <iconPath>Things/Decorations/Armor/Common/PuritySeals/BEWH_Deco_PuritySeal3_south</iconPath>
        <drawnTextureIconPath>Things/Decorations/Armor/Common/PuritySeals/BEWH_Deco_PuritySeal3</drawnTextureIconPath>
        <sortOrder>0</sortOrder>
        <defaultShowRotation>
            <li>North</li>
            <li>South</li>
            <li>East</li>
        </defaultShowRotation>
        <appliesTo>
            <li>BEWH_MkVIIPowerArmor</li>
            <li>BEWH_MkXPowerArmor</li>
        </appliesTo>
		<layerOffsets>
            <li>
                <key>North</key>
                <value>5</value>
            </li>
        </layerOffsets>
        <shaderType>Cutout</shaderType>
        <flipable>true</flipable>
    </Core40k.ExtraDecorationDef>
   
    <Core40k.ExtraDecorationDef>
        <defName>BEWH_DecoPSeal_4</defName>
        <label>Purity seals 4</label>
        <description>...</description>
        <iconPath>Things/Decorations/Armor/Common/PuritySeals/BEWH_Deco_PuritySeal4_south</iconPath>
        <drawnTextureIconPath>Things/Decorations/Armor/Common/PuritySeals/BEWH_Deco_PuritySeal4</drawnTextureIconPath>
        <sortOrder>0</sortOrder>
        <defaultShowRotation>
            <li>South</li>
            <li>West</li>
        </defaultShowRotation>
        <appliesTo>
            <li>BEWH_MkVIIPowerArmor</li>
            <li>BEWH_MkXPowerArmor</li>
        </appliesTo>
        <shaderType>Cutout</shaderType>
        <flipable>true</flipable>
    </Core40k.ExtraDecorationDef>

    <Core40k.ExtraDecorationDef>
        <defName>BEWH_DecoPSeal_5</defName>
        <label>Purity seals 5</label>
        <description>...</description>
        <iconPath>Things/Decorations/Armor/Common/PuritySeals/BEWH_Deco_PuritySeal5_south</iconPath>
        <drawnTextureIconPath>Things/Decorations/Armor/Common/PuritySeals/BEWH_Deco_PuritySeal5</drawnTextureIconPath>
        <sortOrder>0</sortOrder>
        <defaultShowRotation>
            <li>South</li>
            <li>West</li>
            <li>North</li>
        </defaultShowRotation>
        <appliesTo>
            <li>BEWH_MkVIIPowerArmor</li>
            <li>BEWH_MkXPowerArmor</li>
        </appliesTo>
        <shaderType>Cutout</shaderType>
        <flipable>true</flipable>
    </Core40k.ExtraDecorationDef>

    <!-- Relics -->
    <Core40k.ExtraDecorationDef>
        <defName>BEWH_DecoRelic_1</defName>
        <label>Relic 1</label>
        <description>...</description>
        <iconPath>Things/Decorations/Armor/Common/BEWH_Deco_Relic1_south</iconPath>
        <drawnTextureIconPath>Things/Decorations/Armor/Common/BEWH_Deco_Relic1</drawnTextureIconPath>
        <sortOrder>0</sortOrder>
        <defaultShowRotation>
            <li>South</li>
            <li>East</li>
			<li>North</li>
        </defaultShowRotation>
        <appliesTo>
            <li>BEWH_MkVIIPowerArmor</li>
            <li>BEWH_MkXPowerArmor</li>
        </appliesTo>
        <shaderType>Cutout</shaderType>
        <flipable>true</flipable>
    </Core40k.ExtraDecorationDef>

    <!-- Pouches -->
    <Core40k.ExtraDecorationDef>
        <defName>BEWH_DecoPouch_1</defName>
        <label>Pouch 1</label>
        <description>...</description>
        <iconPath>Things/Decorations/Armor/Common/Pouches/BEWH_Deco_Pouch_south</iconPath>
        <drawnTextureIconPath>Things/Decorations/Armor/Common/Pouches/BEWH_Deco_Pouch</drawnTextureIconPath>
        <sortOrder>0</sortOrder>
        <defaultShowRotation>
            <li>North</li>
            <li>East</li>
            <li>South</li>
        </defaultShowRotation>
        <appliesTo>
            <li>BEWH_MkVIIPowerArmor</li>
            <li>BEWH_MkXPowerArmor</li>
        </appliesTo>
        <shaderType>Cutout</shaderType>
        <colourable>true</colourable>
        <availablePresets>
            <li>BEWH_DecoPaletteLeatherBrown</li>
            <li>BEWH_DecoPaletteLeatherBlack</li>
        </availablePresets>
        <flipable>true</flipable>
    </Core40k.ExtraDecorationDef>

    <Core40k.ExtraDecorationDef>
        <defName>BEWH_DecoPouchBelt</defName>
        <label>Pouch belt</label>
        <description>...</description>
        <iconPath>Things/Decorations/Armor/Common/Pouches/BEWH_Deco_PouchesBelt_south</iconPath>
        <drawnTextureIconPath>Things/Decorations/Armor/Common/Pouches/BEWH_Deco_PouchesBelt</drawnTextureIconPath>
        <sortOrder>0</sortOrder>
        <defaultShowRotation>
            <li>North</li>
            <li>East</li>
            <!-- <li>West</li> -->
            <li>South</li>
        </defaultShowRotation>
        <appliesTo>
            <li>BEWH_MkVIIPowerArmor</li>
            <li>BEWH_MkXPowerArmor</li>
        </appliesTo>
        <layerOffsets>
            <li>
                <key>West</key>
                <value>-10</value>
            </li>
            <li>
                <key>East</key>
                <value>-10</value>
            </li>
        </layerOffsets>
        <shaderType>Cutout</shaderType>
        <colourable>true</colourable>
        <availablePresets>
            <li>BEWH_DecoPaletteLeatherBrown</li>
            <li>BEWH_DecoPaletteLeatherBlack</li>
        </availablePresets>
        <flipable>true</flipable>
    </Core40k.ExtraDecorationDef>

    <!-- Grenades -->

    <Core40k.ExtraDecorationDef>
        <defName>BEWH_Deco_Grenade_1</defName>
        <label>Grenade 1</label>
        <description>...</description>
        <iconPath>Things/Decorations/Armor/Common/Grenades/BEWH_Deco_Grenade1_south</iconPath>
        <drawnTextureIconPath>Things/Decorations/Armor/Common/Grenades/BEWH_Deco_Grenade1</drawnTextureIconPath>
        <sortOrder>0</sortOrder>
        <defaultShowRotation>
            <li>North</li>
            <li>East</li>
            <!-- <li>West</li> -->
            <li>South</li>
        </defaultShowRotation>
        <appliesTo>
            <li>BEWH_MkVIIPowerArmor</li>
            <li>BEWH_MkXPowerArmor</li>
        </appliesTo>
        <shaderType>Cutout</shaderType>
        <flipable>true</flipable>
    </Core40k.ExtraDecorationDef>

    <Core40k.ExtraDecorationDef>
        <defName>BEWH_Deco_Grenade_2</defName>
        <label>Grenade 2</label>
        <description>...</description>
        <iconPath>Things/Decorations/Armor/Common/Grenades/BEWH_Deco_Grenade2_south</iconPath>
        <drawnTextureIconPath>Things/Decorations/Armor/Common/Grenades/BEWH_Deco_Grenade2</drawnTextureIconPath>
        <sortOrder>0</sortOrder>
        <defaultShowRotation>
            <li>North</li>
            <!-- <li>East</li> -->
            <li>West</li>
            <li>South</li>
        </defaultShowRotation>
        <appliesTo>
            <li>BEWH_MkVIIPowerArmor</li>
            <li>BEWH_MkXPowerArmor</li>
        </appliesTo>
        <shaderType>Cutout</shaderType>
        <flipable>true</flipable>
    </Core40k.ExtraDecorationDef>

    <Core40k.ExtraDecorationDef>
        <defName>BEWH_Deco_KrGrenade_1</defName>
        <label>Krak Grenade 1</label>
        <description>...</description>
        <iconPath>Things/Decorations/Armor/Common/Grenades/BEWH_Deco_KrakGrenade1_south</iconPath>
        <drawnTextureIconPath>Things/Decorations/Armor/Common/Grenades/BEWH_Deco_KrakGrenade1</drawnTextureIconPath>
        <sortOrder>0</sortOrder>
        <defaultShowRotation>
            <li>North</li>
            <li>East</li>
            <!-- <li>West</li> -->
            <li>South</li>
        </defaultShowRotation>
        <appliesTo>
            <li>BEWH_MkVIIPowerArmor</li>
            <li>BEWH_MkXPowerArmor</li>
        </appliesTo>
        <shaderType>Cutout</shaderType>
        <flipable>true</flipable>
    </Core40k.ExtraDecorationDef>

    <Core40k.ExtraDecorationDef>
        <defName>BEWH_Deco_KrGrenade_2</defName>
        <label>Krak Grenade 2</label>
        <description>...</description>
        <iconPath>Things/Decorations/Armor/Common/Grenades/BEWH_Deco_KrakGrenade2_south</iconPath>
        <drawnTextureIconPath>Things/Decorations/Armor/Common/Grenades/BEWH_Deco_KrakGrenade2</drawnTextureIconPath>
        <sortOrder>0</sortOrder>
        <defaultShowRotation>
            <li>North</li>
            <!-- <li>East</li> -->
            <li>West</li>
            <li>South</li>
        </defaultShowRotation>
        <appliesTo>
            <li>BEWH_MkVIIPowerArmor</li>
            <li>BEWH_MkXPowerArmor</li>
        </appliesTo>
        <shaderType>Cutout</shaderType>
        <flipable>true</flipable>
    </Core40k.ExtraDecorationDef>

    <!-- Misc -->
    <Core40k.ExtraDecorationDef>
        <defName>BEWH_Deco_ClawMarks_1</defName>
        <label>Claw marks</label>
        <description>...</description>
        <iconPath>Things/Decorations/Armor/Common/BEWH_Deco_ClawMarks1_east</iconPath>
        <drawnTextureIconPath>Things/Decorations/Armor/Common/BEWH_Deco_ClawMarks1</drawnTextureIconPath>
        <sortOrder>0</sortOrder>
        <defaultShowRotation>
            <li>North</li>
            <li>South</li>
            <!-- <li>West</li> -->
            <li>East</li>
        </defaultShowRotation>
        <appliesTo>
            <li>BEWH_MkVIIPowerArmor</li>
            <li>BEWH_MkXPowerArmor</li>
        </appliesTo>
        <layerOffsets>
            <li>
                <key>South</key>
                <value>4</value>
            </li>
            <li>
                <key>North</key>
                <value>4</value>
            </li>
        </layerOffsets>
        <shaderType>Cutout</shaderType>
        <flipable>true</flipable>
    </Core40k.ExtraDecorationDef>

    <Core40k.ExtraDecorationDef>
        <defName>BEWH_Deco_Rondel</defName>
        <label>Rondel</label>
        <description>...</description>
        <iconPath>Things/Decorations/Armor/Common/BEWH_Deco_Shield_south</iconPath>
        <drawnTextureIconPath>Things/Decorations/Armor/Common/BEWH_Deco_Shield</drawnTextureIconPath>
        <sortOrder>0</sortOrder>
        <defaultShowRotation>
            <li>North</li>
            <li>South</li>
            <li>West</li>
            <!-- <li>East</li> -->
        </defaultShowRotation>
        <appliesTo>
            <li>BEWH_MkVIIPowerArmor</li>
            <li>BEWH_MkXPowerArmor</li>
        </appliesTo>
        <layerOffsets>
            <li>
                <key>South</key>
                <value>7</value>
            </li>
            <li>
                <key>West</key>
                <value>6</value>
            </li>
            <li>
                <key>East</key>
                <value>6</value>
            </li>
        </layerOffsets>
        <shaderType>Cutout</shaderType>
        <colourable>true</colourable>
        <useArmorColourAsDefault>true</useArmorColourAsDefault>
        <flipable>true</flipable>
    </Core40k.ExtraDecorationDef>
   
    <!-- HEAD STUFF-->
    <!-- Common -->
    <Core40k.ExtraDecorationDef>
        <defName>BEWH_DecoInquisInsignia</defName>
        <label>Inquisition insignia</label>
        <description>...</description>
        <iconPath>Things/Decorations/Headgear/Common/BEWH_Deco_Inquis_south</iconPath>
        <drawnTextureIconPath>Things/Decorations/Headgear/Common/BEWH_Deco_Inquis</drawnTextureIconPath>
        <sortOrder>4</sortOrder>
        <isHelmetDecoration>true</isHelmetDecoration>
        <defaultShowRotation>
            <li>West</li>
            <li>South</li>
            <li>East</li>
        </defaultShowRotation>
        <appliesTo>
            <li>BEWH_MkVIIPowerArmorHelmet</li>
            <li>BEWH_MkXPowerArmorHelmet</li>
        </appliesTo>
        <colourable>true</colourable>
        <availablePresets>
            <li>BEWH_DecoPaletteGold</li>
            <li>BEWH_DecoPaletteSilver</li>
            <li>BEWH_DecoPaletteIFBlack</li>
        </availablePresets>
        <shaderType>Cutout</shaderType>
    </Core40k.ExtraDecorationDef>

    <Core40k.ExtraDecorationDef>
        <defName>BEWH_DecoSkull</defName>
        <label>Skull</label>
        <description>...</description>
        <iconPath>Things/Decorations/Headgear/Common/BEWH_Deco_Skull_south</iconPath>
        <drawnTextureIconPath>Things/Decorations/Headgear/Common/BEWH_Deco_Skull</drawnTextureIconPath>
        <sortOrder>4</sortOrder>
        <isHelmetDecoration>true</isHelmetDecoration>
        <defaultShowRotation>
            <li>West</li>
            <li>South</li>
            <li>East</li>
        </defaultShowRotation>
        <appliesTo>
            <li>BEWH_MkVIIPowerArmorHelmet</li>
            <li>BEWH_MkXPowerArmorHelmet</li>
        </appliesTo>
        <colourable>true</colourable>
        <availablePresets>
            <li>BEWH_DecoPaletteGold</li>
            <li>BEWH_DecoPaletteSilver</li>
            <li>BEWH_DecoPaletteIFBlack</li>
        </availablePresets>
        <shaderType>Cutout</shaderType>
    </Core40k.ExtraDecorationDef>

    <Core40k.ExtraDecorationDef>
        <defName>BEWH_DecoLaurels</defName>
        <label>Laurel wreath</label>
        <description>...</description>
        <iconPath>Things/Decorations/Headgear/Common/BEWH_Deco_Laurel_south</iconPath>
        <drawnTextureIconPath>Things/Decorations/Headgear/Common/BEWH_Deco_Laurel</drawnTextureIconPath>
        <sortOrder>4</sortOrder>
        <isHelmetDecoration>true</isHelmetDecoration>
        <defaultShowRotation>
            <li>West</li>
            <li>South</li>
            <li>East</li>
            <li>North</li>
        </defaultShowRotation>
        <appliesTo>
            <li>BEWH_MkVIIPowerArmorHelmet</li>
            <li>BEWH_MkXPowerArmorHelmet</li>
        </appliesTo>
        <layerOffsets>
            <li>
                <key>East</key>
                <value>1</value>
            </li>
            <li>
                <key>West</key>
                <value>1</value>
            </li>
        </layerOffsets>
        <availablePresets>
            <li>BEWH_DecoPaletteGold</li>
            <li>BEWH_DecoPaletteGreen</li>
            <li>BEWH_DecoPaletteSilver</li>
            <li>BEWH_DecoPaletteIFBlack</li>
        </availablePresets>
        <colourable>true</colourable>
        <shaderType>Cutout</shaderType>
    </Core40k.ExtraDecorationDef>

    <Core40k.ExtraDecorationDef>
        <defName>BEWH_MkxBladeguardBrim</defName>
        <label>Bladeguard brim</label>
        <description>...</description>
        <iconPath>Things/Decorations/Headgear/MkX/BEWH_Deco_MkxBladeguardShield_south</iconPath>
        <drawnTextureIconPath>Things/Decorations/Headgear/MkX/BEWH_Deco_MkxBladeguardShield</drawnTextureIconPath>
        <sortOrder>4</sortOrder>
        <isHelmetDecoration>true</isHelmetDecoration>
        <defaultShowRotation>
            <li>West</li>
            <li>South</li>
            <li>East</li>
        </defaultShowRotation>
        <appliesTo>
            <li>BEWH_MkXPowerArmorHelmet</li>
            <li>BEWH_MkVIIPowerArmorHelmet</li>
        </appliesTo>
        <colourable>true</colourable>
        <hasArmorColourPaletteOption>true</hasArmorColourPaletteOption>
        <useArmorColourAsDefault>true</useArmorColourAsDefault>
        <layerOffsets>
            <li>
                <key>East</key>
                <value>-3</value>
            </li>
            <li>
                <key>West</key>
                <value>-3</value>
            </li>
        </layerOffsets>
        <availablePresets>
            <li>BEWH_DecoPaletteGold</li>
            <li>BEWH_DecoPaletteSilver</li>
            <li>BEWH_DecoPaletteIFBlack</li>
            <li>BEWH_DecoPaletteStripeRed</li>
        </availablePresets>
        <shaderType>Cutout</shaderType>
    </Core40k.ExtraDecorationDef>

    <!-- Mark X -->
    <Core40k.ExtraDecorationDef>
        <defName>BEWH_MkxDecoStripe</defName>
        <label>Stripe</label>
        <description>...</description>
        <iconPath>Things/Decorations/Headgear/MkX/BEWH_Deco_MkxStripe_south</iconPath>
        <drawnTextureIconPath>Things/Decorations/Headgear/MkX/BEWH_Deco_MkxStripe</drawnTextureIconPath>
        <sortOrder>4</sortOrder>
        <isHelmetDecoration>true</isHelmetDecoration>
        <defaultShowRotation>
            <li>West</li>
            <li>South</li>
            <li>East</li>
            <li>North</li>
        </defaultShowRotation>
        <appliesTo>
            <li>BEWH_MkXPowerArmorHelmet</li>
        </appliesTo>
        <colourable>true</colourable>
        <layerOffsets>
            <li>
                <key>South</key>
                <value>-1</value>
            </li>
            <li>
                <key>East</key>
                <value>-4</value>
            </li>
            <li>
                <key>West</key>
                <value>-6</value>
            </li>
        </layerOffsets>
        <availablePresets>
            <li>BEWH_DecoPaletteGold</li>
            <!-- <li>BEWH_DecoPaletteGreen</li> -->
            <li>BEWH_DecoPaletteSilver</li>
            <li>BEWH_DecoPaletteIFBlack</li>
            <li>BEWH_DecoPaletteStripeRed</li>
        </availablePresets>
        <shaderType>Cutout</shaderType>
    </Core40k.ExtraDecorationDef>

    <Core40k.ExtraDecorationDef>
        <defName>BEWH_MkxLieutenantStripe</defName>
        <label>Lieutenant stripe</label>
        <description>...</description>
        <iconPath>Things/Decorations/Headgear/MkX/BEWH_Deco_MkxLieutenantStripe_south</iconPath>
        <drawnTextureIconPath>Things/Decorations/Headgear/MkX/BEWH_Deco_MkxLieutenantStripe</drawnTextureIconPath>
        <sortOrder>4</sortOrder>
        <isHelmetDecoration>true</isHelmetDecoration>
        <defaultShowRotation>
            <li>West</li>
            <li>South</li>
            <li>East</li>
            <li>North</li>
        </defaultShowRotation>
        <appliesTo>
            <li>BEWH_MkXPowerArmorHelmet</li>
        </appliesTo>
        <colourable>false</colourable>
        <layerOffsets>
            <li>
                <key>South</key>
                <value>-1</value>
            </li>
            <li>
                <key>East</key>
                <value>-4</value>
            </li>
            <li>
                <key>West</key>
                <value>-5</value>
            </li>
        </layerOffsets>
        <shaderType>Cutout</shaderType>
    </Core40k.ExtraDecorationDef>

    <Core40k.ExtraDecorationDef>
        <defName>BEWH_MkXclawMarks_1</defName>
        <label>Claw marks 1</label>
        <description>...</description>
        <iconPath>Things/Decorations/Headgear/MkX/BEWH_Deco_ClawMarks1MkX_south</iconPath>
        <drawnTextureIconPath>Things/Decorations/Headgear/MkX/BEWH_Deco_ClawMarks1MkX</drawnTextureIconPath>
        <sortOrder>4</sortOrder>
        <isHelmetDecoration>true</isHelmetDecoration>
        <defaultShowRotation>
            <li>West</li>
            <li>South</li>
			<li>North</li>
        </defaultShowRotation>
        <appliesTo>
            <li>BEWH_MkXPowerArmorHelmet</li>
        </appliesTo>
        <flipable>true</flipable>
        <shaderType>Cutout</shaderType>
    </Core40k.ExtraDecorationDef>

    <Core40k.ExtraDecorationDef>
        <defName>BEWH_MkXclawMarks_2</defName>
        <label>Claw marks 2</label>
        <description>...</description>
        <iconPath>Things/Decorations/Headgear/MkX/BEWH_Deco_ClawMarks2MkX_south</iconPath>
        <drawnTextureIconPath>Things/Decorations/Headgear/MkX/BEWH_Deco_ClawMarks2MkX</drawnTextureIconPath>
        <sortOrder>4</sortOrder>
        <isHelmetDecoration>true</isHelmetDecoration>
        <defaultShowRotation>
            <li>West</li>
            <li>South</li>
			<li>North</li>
        </defaultShowRotation>
        <appliesTo>
            <li>BEWH_MkXPowerArmorHelmet</li>
        </appliesTo>
        <flipable>true</flipable>
        <shaderType>Cutout</shaderType>
    </Core40k.ExtraDecorationDef>

    <!-- Mark VII -->
    <Core40k.ExtraDecorationDef>
        <defName>BEWH_MkVIIDecoStripe</defName>
        <label>Stripe</label>
        <description>...</description>
        <iconPath>Things/Decorations/Headgear/MkVII/BEWH_Deco_MkVIIStripe_south</iconPath>
        <drawnTextureIconPath>Things/Decorations/Headgear/MkVII/BEWH_Deco_MkVIIStripe</drawnTextureIconPath>
        <sortOrder>4</sortOrder>
        <isHelmetDecoration>true</isHelmetDecoration>
        <defaultShowRotation>
            <li>West</li>
            <li>South</li>
            <li>East</li>
            <li>North</li>
        </defaultShowRotation>
        <appliesTo>
            <li>BEWH_MkVIIPowerArmorHelmet</li>
        </appliesTo>
        <colourable>true</colourable>
        <layerOffsets>
            <li>
                <key>South</key>
                <value>-1</value>
            </li>
            <li>
                <key>East</key>
                <value>-4</value>
            </li>
            <li>
                <key>West</key>
                <value>-6</value>
            </li>
        </layerOffsets>
        <availablePresets>
            <li>BEWH_DecoPaletteGold</li>
            <!-- <li>BEWH_DecoPaletteGreen</li> -->
            <li>BEWH_DecoPaletteSilver</li>
            <li>BEWH_DecoPaletteIFBlack</li>
            <li>BEWH_DecoPaletteStripeRed</li>
        </availablePresets>
        <shaderType>Cutout</shaderType>
    </Core40k.ExtraDecorationDef>

    <Core40k.ExtraDecorationDef>
        <defName>BEWH_MkVIILieutenantStripe</defName>
        <label>Lieutenant stripe</label>
        <description>...</description>
        <iconPath>Things/Decorations/Headgear/MkVII/BEWH_Deco_MkVIILieutenantStripe_south</iconPath>
        <drawnTextureIconPath>Things/Decorations/Headgear/MkVII/BEWH_Deco_MkVIILieutenantStripe</drawnTextureIconPath>
        <sortOrder>4</sortOrder>
        <isHelmetDecoration>true</isHelmetDecoration>
        <defaultShowRotation>
            <li>West</li>
            <li>South</li>
            <li>East</li>
            <li>North</li>
        </defaultShowRotation>
        <appliesTo>
            <li>BEWH_MkVIIPowerArmorHelmet</li>
        </appliesTo>
        <colourable>false</colourable>
        <layerOffsets>
            <li>
                <key>South</key>
                <value>-1</value>
            </li>
            <li>
                <key>East</key>
                <value>-4</value>
            </li>
            <li>
                <key>West</key>
                <value>-5</value>
            </li>
        </layerOffsets>
        <shaderType>Cutout</shaderType>
    </Core40k.ExtraDecorationDef>

    <Core40k.ExtraDecorationDef>
        <defName>BEWH_MkVIIclawMarks_1</defName>
        <label>Claw marks 1</label>
        <description>...</description>
        <iconPath>Things/Decorations/Headgear/MkVII/BEWH_Deco_ClawMarks1MkVII_south</iconPath>
        <drawnTextureIconPath>Things/Decorations/Headgear/MkVII/BEWH_Deco_ClawMarks1MkVII</drawnTextureIconPath>
        <sortOrder>4</sortOrder>
        <isHelmetDecoration>true</isHelmetDecoration>
        <defaultShowRotation>
            <li>West</li>
            <li>South</li>
			<li>North</li>
        </defaultShowRotation>
        <appliesTo>
            <li>BEWH_MkVIIPowerArmorHelmet</li>
        </appliesTo>
        <flipable>true</flipable>
        <shaderType>Cutout</shaderType>
    </Core40k.ExtraDecorationDef>

    <Core40k.ExtraDecorationDef>
        <defName>BEWH_MkVIIclawMarks_2</defName>
        <label>Claw marks 2</label>
        <description>...</description>
        <iconPath>Things/Decorations/Headgear/MkVII/BEWH_Deco_ClawMarks2MkVII_south</iconPath>
        <drawnTextureIconPath>Things/Decorations/Headgear/MkVII/BEWH_Deco_ClawMarks2MkVII</drawnTextureIconPath>
        <sortOrder>4</sortOrder>
        <isHelmetDecoration>true</isHelmetDecoration>
        <defaultShowRotation>
            <li>West</li>
            <li>South</li>
			<li>North</li>
        </defaultShowRotation>
        <appliesTo>
            <li>BEWH_MkVIIPowerArmorHelmet</li>
        </appliesTo>
        <flipable>true</flipable>
        <shaderType>Cutout</shaderType>
    </Core40k.ExtraDecorationDef>
    
</Defs>